<?xml version = '1.0' encoding = 'UTF-8'?>
<FKIndexAssociation class="oracle.dbtools.crest.model.design.relational.FKIndexAssociation" directorySegmentName="seg_0" id="940644B7-ABB7-161E-D5C9-A2FDFE4FDBA2" containerWithKeyObject="2994A2D9-C5FD-76A0-3999-838EDEF9C575" localFKIndex="D1EE275D-FC96-DDA2-1FBD-3691938B24F1" name="DEPARTAMENTO_ESTADO_FK">
<createdBy>Pipe</createdBy>
<createdTime>2020-09-25 18:51:28 UTC</createdTime>
<ownerDesignName>Portafolio_BDD</ownerDesignName>
<referredTableLongName>ESTADO</referredTableLongName>
<deleteRule>NO ACTION</deleteRule>
<referredTableID>1B1B7AEE-050C-A418-BC3E-2B0301ECFE66</referredTableID>
<keyObject>7E4AB875-88D5-9004-AA6A-34C53EC31BEA</keyObject>
<referredKeyID>7E4AB875-88D5-9004-AA6A-34C53EC31BEA</referredKeyID>
<mandatory>true</mandatory>
<refColNames>id_estado</refColNames>
<transferable>true</transferable>
<rely>false</rely>
<columnDependencyConstraintGenerateInDDL>true</columnDependencyConstraintGenerateInDDL>
</FKIndexAssociation>